t3w/__init__.py
t3w/core.py
t3w/plugins/__init__.py
t3w/plugins/model_select.py
t3w/plugins/tqdm.py
t3w/plugins/aim/__init__.py
t3w/plugins/aim/patch.py
t3w/plugins/aim/side_effect.py
t3w/utils/__init__.py
t3w/utils/argparse.py
t3w/utils/dataset_cache.py
t3w/utils/misc.py
t3w/utils/subcommand.py
t3w/utils/torchsummaryX.py
t3w/utils/verbose.py
t3w-0.3.3.dist-info/LICENSE
t3w-0.3.3.dist-info/METADATA
t3w-0.3.3.dist-info/WHEEL
t3w-0.3.3.dist-info/top_level.txt
t3w-0.3.3.dist-info/RECORD
