Metadata-Version: 2.1
Name: t3w
Version: 0.3.3
Summary: Typed Thin PyTorch Wrapper
Home-page: https://github.com/tjyuyao/t3w
Author: Yuyao Huang
Author-email: huangyuyao@outlook.com
License-File: LICENSE
Requires-Dist: jaxtyping
Requires-Dist: pandas
Requires-Dist: aim
Requires-Dist: tqdm
Requires-Dist: rich
Requires-Dist: docstring-parser
Requires-Dist: typing-inspect
Requires-Dist: tblib
